django_entangled-0.7.dist-info/licenses/LICENSE
entangled/__init__.py
entangled/forms.py
entangled/utils.py
django_entangled-0.7.dist-info/METADATA
django_entangled-0.7.dist-info/WHEEL
django_entangled-0.7.dist-info/top_level.txt
django_entangled-0.7.dist-info/RECORD
